mkdocs_tree_title/__init__.py
mkdocs_tree_title/plugin.py
mkdocs_tree_title-0.1.1.dist-info/LICENSE
mkdocs_tree_title-0.1.1.dist-info/METADATA
mkdocs_tree_title-0.1.1.dist-info/WHEEL
mkdocs_tree_title-0.1.1.dist-info/entry_points.txt
mkdocs_tree_title-0.1.1.dist-info/top_level.txt
mkdocs_tree_title-0.1.1.dist-info/RECORD
